ray_provider/__init__.py
ray_provider/constants.py
ray_provider/decorators.py
ray_provider/exceptions.py
ray_provider/hooks.py
ray_provider/operators.py
ray_provider/triggers.py
astro_provider_ray-0.3.1.dist-info/METADATA
astro_provider_ray-0.3.1.dist-info/WHEEL
astro_provider_ray-0.3.1.dist-info/entry_points.txt
astro_provider_ray-0.3.1.dist-info/licenses/LICENSE
astro_provider_ray-0.3.1.dist-info/RECORD
