Metadata-Version: 2.4
Name: astro-provider-ray
Version: 0.3.1
Summary: An Apache Airflow provider package built by Astronomer to integrate with Ray.
Project-URL: Homepage, https://astronomer.io
Project-URL: Source, https://github.com/astronomer/astro-provider-ray/
Author-email: Astronomer <humans@astronomer.io>
License: Apache License 2.0
License-File: LICENSE
Classifier: Framework :: Apache Airflow
Classifier: Framework :: Apache Airflow :: Provider
Classifier: Intended Audience :: Developers
Classifier: License :: OSI Approved :: Apache Software License
Classifier: Operating System :: OS Independent
Classifier: Programming Language :: Python
Classifier: Programming Language :: Python :: 3
Classifier: Programming Language :: Python :: 3.8
Classifier: Programming Language :: Python :: 3.9
Classifier: Programming Language :: Python :: 3.10
Classifier: Programming Language :: Python :: 3.11
Classifier: Programming Language :: Python :: 3.12
Requires-Python: <3.13,>=3.8
Requires-Dist: apache-airflow-providers-cncf-kubernetes
Requires-Dist: apache-airflow>=2.7
Requires-Dist: kubernetes
Requires-Dist: pytest
Requires-Dist: pytest-asyncio
Requires-Dist: pyyaml
Requires-Dist: ray[default]
Requires-Dist: requests
Provides-Extra: tests
Requires-Dist: build; extra == 'tests'
